apksums/__init__.py
apksums/main.py
apksums-0.1.2.dist-info/METADATA
apksums-0.1.2.dist-info/WHEEL
apksums-0.1.2.dist-info/entry_points.txt
apksums-0.1.2.dist-info/licenses/LICENSE
apksums-0.1.2.dist-info/RECORD
