Metadata-Version: 2.4
Name: apksums
Version: 0.1.2
Summary: Verify checksums of installed APK package files
Project-URL: Homepage, https://github.com/jontyms/apksums
Project-URL: Repository, https://github.com/jontyms/apksums.git
Project-URL: Bug Tracker, https://github.com/jontyms/apksums/issues
Author-email: Jstyles <python@styl.dev>
License: Copyright 2025 Jstyles
License-File: LICENSE
Keywords: alpine,apk,checksums,security,verification
Classifier: Development Status :: 4 - Beta
Classifier: Environment :: Console
Classifier: Intended Audience :: System Administrators
Classifier: License :: OSI Approved :: MIT License
Classifier: Operating System :: POSIX :: Linux
Classifier: Programming Language :: Python :: 3
Classifier: Programming Language :: Python :: 3.7
Classifier: Programming Language :: Python :: 3.8
Classifier: Programming Language :: Python :: 3.9
Classifier: Programming Language :: Python :: 3.10
Classifier: Programming Language :: Python :: 3.11
Classifier: Topic :: Security :: Cryptography
Classifier: Topic :: System :: Systems Administration
Requires-Python: >=3.7
